ents/__init__.py
ents/cli.py
ents/calibrate/PingSMU.py
ents/calibrate/PingSPS.py
ents/calibrate/README.md
ents/calibrate/__init__.py
ents/calibrate/linear_regression.py
ents/calibrate/plots.py
ents/calibrate/recorder.py
ents/config/README.md
ents/config/__init__.py
ents/config/adv_trace.py
ents/config/user_config.py
ents/proto/__init__.py
ents/proto/decode.py
ents/proto/encode.py
ents/proto/esp32.py
ents/proto/sensor.py
ents/proto/sensor_pb2.py
ents/proto/soil_power_sensor_pb2.py
ents/simulator/__init__.py
ents/simulator/node.py
ents-2.3.5.dist-info/METADATA
ents-2.3.5.dist-info/WHEEL
ents-2.3.5.dist-info/entry_points.txt
ents-2.3.5.dist-info/licenses/LICENSE
ents-2.3.5.dist-info/RECORD
