Metadata-Version: 2.4
Name: ents
Version: 2.3.5
Summary: Python package for Environmental NeTworked Sensor (ENTS)
Project-URL: Homepage, https://github.com/jlab-sensing/soil-power-sensor-firmware
Project-URL: Issues, https://github.com/jlab-sensing/soil-power-sensor-firmware/issues
Author-email: John Madden <jmadden173@pm.me>
License-File: LICENSE
Classifier: License :: OSI Approved :: MIT License
Classifier: Operating System :: OS Independent
Classifier: Programming Language :: Python :: 3
Requires-Python: >=3.11
Requires-Dist: matplotlib
Requires-Dist: pandas
Requires-Dist: protobuf==6.33.2
Requires-Dist: pyserial
Requires-Dist: requests
Requires-Dist: scikit-learn
Requires-Dist: tqdm
Provides-Extra: dev
Requires-Dist: black; extra == 'dev'
Requires-Dist: ruff; extra == 'dev'
Provides-Extra: gui
Requires-Dist: pyqt5; extra == 'gui'
